differintC/__init__.py
differintC/_differintC.pyd
differintC/_differintC.pyi
differintC/_version.py
differintC/libfftw3-3.dll
differintC/libfftw3-3.lib
differintc-0.0.3.dist-info/METADATA
differintc-0.0.3.dist-info/WHEEL
differintc-0.0.3.dist-info/licenses/LICENSE
differintc-0.0.3.dist-info/RECORD
