Metadata-Version: 2.2
Name: differintC
Version: 0.0.3
Summary: Fast C++ implementation of fractional calculus operators via pybind11
Author: Parsa Roshanak
License: GPL-3.0-or-later
Classifier: Development Status :: 3 - Alpha
Classifier: License :: OSI Approved :: GNU General Public License v3 or later (GPLv3+)
Classifier: Programming Language :: Python
Classifier: Programming Language :: Python :: 3
Classifier: Programming Language :: Python :: 3.8
Classifier: Programming Language :: Python :: 3.9
Classifier: Programming Language :: Python :: 3.10
Classifier: Programming Language :: Python :: 3.11
Classifier: Programming Language :: Python :: 3.12
Classifier: Programming Language :: Python :: 3.13
Classifier: Programming Language :: C++
Classifier: Topic :: Scientific/Engineering :: Mathematics
Classifier: Intended Audience :: Science/Research
Project-URL: Homepage, https://github.com/iparsw/differintC
Project-URL: Repository, https://github.com/iparsw/differintC
Project-URL: Issues, https://github.com/iparsw/differintC/issues
Requires-Python: >=3.8
